smot/__init__.py
smot/algorithm.py
smot/classes.py
smot/format.py
smot/main.py
smot/parser.py
smot/py.typed
smot/util.py
smot/version.py
smot-0.17.4.dist-info/LICENSE
smot-0.17.4.dist-info/METADATA
smot-0.17.4.dist-info/WHEEL
smot-0.17.4.dist-info/entry_points.txt
smot-0.17.4.dist-info/top_level.txt
smot-0.17.4.dist-info/RECORD
