Metadata-Version: 2.1
Name: smot
Version: 0.17.4
Summary: simple manipulation of trees
Home-page: https://github.com/flu-crew/smot
Author: Zebulun Arendsee
Author-email: zebulun.arendsee@usda.gov
License: UNKNOWN
Platform: UNKNOWN
Classifier: Programming Language :: Python :: 3
Classifier: License :: OSI Approved :: MIT License
Classifier: Operating System :: OS Independent
License-File: LICENSE
Requires-Dist: parsec
Requires-Dist: click
